[
  {
    "MateriaGroupId": 1,
    "MateriaId": 2101001
  },
  {
    "MateriaGroupId": 1,
    "MateriaId": 2101003
  },
  {
    "MateriaGroupId": 1,
    "MateriaId": 2102001
  },
  {
    "MateriaGroupId": 1,
    "MateriaId": 2102003
  },
  {
    "MateriaGroupId": 1,
    "MateriaId": 2111001
  },
  {
    "MateriaGroupId": 1,
    "MateriaId": 2111003
  },
  {
    "MateriaGroupId": 1,
    "MateriaId": 2111007
  },
  {
    "MateriaGroupId": 1,
    "MateriaId": 2112001
  },
  {
    "MateriaGroupId": 1,
    "MateriaId": 2112003
  },
  {
    "MateriaGroupId": 1,
    "MateriaId": 2112004
  },
  {
    "MateriaGroupId": 1,
    "MateriaId": 2112005
  },
  {
    "MateriaGroupId": 1,
    "MateriaId": 2112006
  },
  {
    "MateriaGroupId": 1,
    "MateriaId": 2112007
  },
  {
    "MateriaGroupId": 1,
    "MateriaId": 2112008
  },
  {
    "MateriaGroupId": 1,
    "MateriaId": 2112009
  },
  {
    "MateriaGroupId": 1,
    "MateriaId": 2112010
  },
  {
    "MateriaGroupId": 1,
    "MateriaId": 2112011
  },
  {
    "MateriaGroupId": 1,
    "MateriaId": 2121001
  },
  {
    "MateriaGroupId": 1,
    "MateriaId": 2121003
  },
  {
    "MateriaGroupId": 1,
    "MateriaId": 2121007
  },
  {
    "MateriaGroupId": 1,
    "MateriaId": 2122001
  },
  {
    "MateriaGroupId": 1,
    "MateriaId": 2122003
  },
  {
    "MateriaGroupId": 1,
    "MateriaId": 2122004
  },
  {
    "MateriaGroupId": 1,
    "MateriaId": 2122005
  },
  {
    "MateriaGroupId": 1,
    "MateriaId": 2122006
  },
  {
    "MateriaGroupId": 1,
    "MateriaId": 2122007
  },
  {
    "MateriaGroupId": 1,
    "MateriaId": 2122008
  },
  {
    "MateriaGroupId": 1,
    "MateriaId": 2122009
  },
  {
    "MateriaGroupId": 1,
    "MateriaId": 2122010
  },
  {
    "MateriaGroupId": 1,
    "MateriaId": 2122011
  },
  {
    "MateriaGroupId": 1,
    "MateriaId": 2131001
  },
  {
    "MateriaGroupId": 1,
    "MateriaId": 2131003
  },
  {
    "MateriaGroupId": 1,
    "MateriaId": 2131007
  },
  {
    "MateriaGroupId": 1,
    "MateriaId": 2132001
  },
  {
    "MateriaGroupId": 1,
    "MateriaId": 2132003
  },
  {
    "MateriaGroupId": 1,
    "MateriaId": 2132004
  },
  {
    "MateriaGroupId": 1,
    "MateriaId": 2132005
  },
  {
    "MateriaGroupId": 1,
    "MateriaId": 2132006
  },
  {
    "MateriaGroupId": 1,
    "MateriaId": 2132007
  },
  {
    "MateriaGroupId": 1,
    "MateriaId": 2132008
  },
  {
    "MateriaGroupId": 1,
    "MateriaId": 2132009
  },
  {
    "MateriaGroupId": 1,
    "MateriaId": 2132010
  },
  {
    "MateriaGroupId": 1,
    "MateriaId": 2132011
  },
  {
    "MateriaGroupId": 1,
    "MateriaId": 2141001
  },
  {
    "MateriaGroupId": 1,
    "MateriaId": 2141002
  },
  {
    "MateriaGroupId": 1,
    "MateriaId": 2141007
  },
  {
    "MateriaGroupId": 1,
    "MateriaId": 2142001
  },
  {
    "MateriaGroupId": 1,
    "MateriaId": 2142002
  },
  {
    "MateriaGroupId": 1,
    "MateriaId": 2142003
  },
  {
    "MateriaGroupId": 1,
    "MateriaId": 2142004
  },
  {
    "MateriaGroupId": 1,
    "MateriaId": 2142005
  },
  {
    "MateriaGroupId": 1,
    "MateriaId": 2142006
  },
  {
    "MateriaGroupId": 1,
    "MateriaId": 2142007
  },
  {
    "MateriaGroupId": 1,
    "MateriaId": 2142008
  },
  {
    "MateriaGroupId": 1,
    "MateriaId": 2142009
  },
  {
    "MateriaGroupId": 1,
    "MateriaId": 2142010
  },
  {
    "MateriaGroupId": 1,
    "MateriaId": 2151001
  },
  {
    "MateriaGroupId": 1,
    "MateriaId": 2151002
  },
  {
    "MateriaGroupId": 1,
    "MateriaId": 2151007
  },
  {
    "MateriaGroupId": 1,
    "MateriaId": 2152001
  },
  {
    "MateriaGroupId": 1,
    "MateriaId": 2152002
  },
  {
    "MateriaGroupId": 1,
    "MateriaId": 2152003
  },
  {
    "MateriaGroupId": 1,
    "MateriaId": 2152004
  },
  {
    "MateriaGroupId": 1,
    "MateriaId": 2152005
  },
  {
    "MateriaGroupId": 1,
    "MateriaId": 2152006
  },
  {
    "MateriaGroupId": 1,
    "MateriaId": 2152007
  },
  {
    "MateriaGroupId": 1,
    "MateriaId": 2152008
  },
  {
    "MateriaGroupId": 1,
    "MateriaId": 2152009
  },
  {
    "MateriaGroupId": 1,
    "MateriaId": 2152010
  },
  {
    "MateriaGroupId": 1,
    "MateriaId": 2161001
  },
  {
    "MateriaGroupId": 1,
    "MateriaId": 2161002
  },
  {
    "MateriaGroupId": 1,
    "MateriaId": 2161007
  },
  {
    "MateriaGroupId": 1,
    "MateriaId": 2162001
  },
  {
    "MateriaGroupId": 1,
    "MateriaId": 2162002
  },
  {
    "MateriaGroupId": 1,
    "MateriaId": 2162003
  },
  {
    "MateriaGroupId": 1,
    "MateriaId": 2162004
  },
  {
    "MateriaGroupId": 1,
    "MateriaId": 2162005
  },
  {
    "MateriaGroupId": 1,
    "MateriaId": 2162006
  },
  {
    "MateriaGroupId": 1,
    "MateriaId": 2162007
  },
  {
    "MateriaGroupId": 1,
    "MateriaId": 2162008
  },
  {
    "MateriaGroupId": 1,
    "MateriaId": 2162009
  },
  {
    "MateriaGroupId": 1,
    "MateriaId": 2162010
  },
  {
    "MateriaGroupId": 1,
    "MateriaId": 2200001
  },
  {
    "MateriaGroupId": 1,
    "MateriaId": 2300001
  },
  {
    "MateriaGroupId": 1,
    "MateriaId": 2300002
  },
  {
    "MateriaGroupId": 1,
    "MateriaId": 2400001
  },
  {
    "MateriaGroupId": 1,
    "MateriaId": 2400002
  },
  {
    "MateriaGroupId": 1,
    "MateriaId": 2400003
  },
  {
    "MateriaGroupId": 1,
    "MateriaId": 2400004
  },
  {
    "MateriaGroupId": 1,
    "MateriaId": 2400005
  },
  {
    "MateriaGroupId": 1,
    "MateriaId": 2501001
  },
  {
    "MateriaGroupId": 1,
    "MateriaId": 2601001
  },
  {
    "MateriaGroupId": 1,
    "MateriaId": 2601002
  },
  {
    "MateriaGroupId": 1,
    "MateriaId": 2601003
  },
  {
    "MateriaGroupId": 1,
    "MateriaId": 2601004
  },
  {
    "MateriaGroupId": 1,
    "MateriaId": 2601005
  },
  {
    "MateriaGroupId": 1,
    "MateriaId": 2601006
  },
  {
    "MateriaGroupId": 1,
    "MateriaId": 2601007
  },
  {
    "MateriaGroupId": 1,
    "MateriaId": 2601008
  },
  {
    "MateriaGroupId": 1,
    "MateriaId": 2601009
  },
  {
    "MateriaGroupId": 1,
    "MateriaId": 2601010
  },
  {
    "MateriaGroupId": 1,
    "MateriaId": 2601011
  },
  {
    "MateriaGroupId": 2,
    "MateriaId": 2101001
  },
  {
    "MateriaGroupId": 2,
    "MateriaId": 2102001
  },
  {
    "MateriaGroupId": 2,
    "MateriaId": 2111001
  },
  {
    "MateriaGroupId": 2,
    "MateriaId": 2111007
  },
  {
    "MateriaGroupId": 2,
    "MateriaId": 2112001
  },
  {
    "MateriaGroupId": 2,
    "MateriaId": 2112004
  },
  {
    "MateriaGroupId": 2,
    "MateriaId": 2112005
  },
  {
    "MateriaGroupId": 2,
    "MateriaId": 2112006
  },
  {
    "MateriaGroupId": 2,
    "MateriaId": 2112007
  },
  {
    "MateriaGroupId": 2,
    "MateriaId": 2121001
  },
  {
    "MateriaGroupId": 2,
    "MateriaId": 2121007
  },
  {
    "MateriaGroupId": 2,
    "MateriaId": 2122001
  },
  {
    "MateriaGroupId": 2,
    "MateriaId": 2122004
  },
  {
    "MateriaGroupId": 2,
    "MateriaId": 2122005
  },
  {
    "MateriaGroupId": 2,
    "MateriaId": 2122006
  },
  {
    "MateriaGroupId": 2,
    "MateriaId": 2122007
  },
  {
    "MateriaGroupId": 2,
    "MateriaId": 2131001
  },
  {
    "MateriaGroupId": 2,
    "MateriaId": 2131007
  },
  {
    "MateriaGroupId": 2,
    "MateriaId": 2132001
  },
  {
    "MateriaGroupId": 2,
    "MateriaId": 2132004
  },
  {
    "MateriaGroupId": 2,
    "MateriaId": 2132005
  },
  {
    "MateriaGroupId": 2,
    "MateriaId": 2132006
  },
  {
    "MateriaGroupId": 2,
    "MateriaId": 2132007
  },
  {
    "MateriaGroupId": 2,
    "MateriaId": 2141001
  },
  {
    "MateriaGroupId": 2,
    "MateriaId": 2141007
  },
  {
    "MateriaGroupId": 2,
    "MateriaId": 2142001
  },
  {
    "MateriaGroupId": 2,
    "MateriaId": 2142003
  },
  {
    "MateriaGroupId": 2,
    "MateriaId": 2142004
  },
  {
    "MateriaGroupId": 2,
    "MateriaId": 2142005
  },
  {
    "MateriaGroupId": 2,
    "MateriaId": 2142006
  },
  {
    "MateriaGroupId": 2,
    "MateriaId": 2151001
  },
  {
    "MateriaGroupId": 2,
    "MateriaId": 2151007
  },
  {
    "MateriaGroupId": 2,
    "MateriaId": 2152001
  },
  {
    "MateriaGroupId": 2,
    "MateriaId": 2152003
  },
  {
    "MateriaGroupId": 2,
    "MateriaId": 2152004
  },
  {
    "MateriaGroupId": 2,
    "MateriaId": 2152005
  },
  {
    "MateriaGroupId": 2,
    "MateriaId": 2152006
  },
  {
    "MateriaGroupId": 2,
    "MateriaId": 2161001
  },
  {
    "MateriaGroupId": 2,
    "MateriaId": 2161007
  },
  {
    "MateriaGroupId": 2,
    "MateriaId": 2162001
  },
  {
    "MateriaGroupId": 2,
    "MateriaId": 2162003
  },
  {
    "MateriaGroupId": 2,
    "MateriaId": 2162004
  },
  {
    "MateriaGroupId": 2,
    "MateriaId": 2162005
  },
  {
    "MateriaGroupId": 2,
    "MateriaId": 2162006
  },
  {
    "MateriaGroupId": 2,
    "MateriaId": 2501001
  },
  {
    "MateriaGroupId": 2,
    "MateriaId": 2601001
  },
  {
    "MateriaGroupId": 2,
    "MateriaId": 2601002
  },
  {
    "MateriaGroupId": 2,
    "MateriaId": 2601003
  },
  {
    "MateriaGroupId": 2,
    "MateriaId": 2601004
  },
  {
    "MateriaGroupId": 2,
    "MateriaId": 2601005
  },
  {
    "MateriaGroupId": 2,
    "MateriaId": 2601006
  },
  {
    "MateriaGroupId": 2,
    "MateriaId": 2601007
  },
  {
    "MateriaGroupId": 2,
    "MateriaId": 2601008
  },
  {
    "MateriaGroupId": 2,
    "MateriaId": 2601009
  },
  {
    "MateriaGroupId": 2,
    "MateriaId": 2601010
  },
  {
    "MateriaGroupId": 3,
    "MateriaId": 2101003
  },
  {
    "MateriaGroupId": 3,
    "MateriaId": 2102003
  },
  {
    "MateriaGroupId": 3,
    "MateriaId": 2111003
  },
  {
    "MateriaGroupId": 3,
    "MateriaId": 2112003
  },
  {
    "MateriaGroupId": 3,
    "MateriaId": 2112008
  },
  {
    "MateriaGroupId": 3,
    "MateriaId": 2112009
  },
  {
    "MateriaGroupId": 3,
    "MateriaId": 2112010
  },
  {
    "MateriaGroupId": 3,
    "MateriaId": 2112011
  },
  {
    "MateriaGroupId": 3,
    "MateriaId": 2121003
  },
  {
    "MateriaGroupId": 3,
    "MateriaId": 2122003
  },
  {
    "MateriaGroupId": 3,
    "MateriaId": 2122008
  },
  {
    "MateriaGroupId": 3,
    "MateriaId": 2122009
  },
  {
    "MateriaGroupId": 3,
    "MateriaId": 2122010
  },
  {
    "MateriaGroupId": 3,
    "MateriaId": 2122011
  },
  {
    "MateriaGroupId": 3,
    "MateriaId": 2131003
  },
  {
    "MateriaGroupId": 3,
    "MateriaId": 2132003
  },
  {
    "MateriaGroupId": 3,
    "MateriaId": 2132008
  },
  {
    "MateriaGroupId": 3,
    "MateriaId": 2132009
  },
  {
    "MateriaGroupId": 3,
    "MateriaId": 2132010
  },
  {
    "MateriaGroupId": 3,
    "MateriaId": 2132011
  },
  {
    "MateriaGroupId": 3,
    "MateriaId": 2141002
  },
  {
    "MateriaGroupId": 3,
    "MateriaId": 2142002
  },
  {
    "MateriaGroupId": 3,
    "MateriaId": 2142007
  },
  {
    "MateriaGroupId": 3,
    "MateriaId": 2142008
  },
  {
    "MateriaGroupId": 3,
    "MateriaId": 2142009
  },
  {
    "MateriaGroupId": 3,
    "MateriaId": 2142010
  },
  {
    "MateriaGroupId": 3,
    "MateriaId": 2151002
  },
  {
    "MateriaGroupId": 3,
    "MateriaId": 2152002
  },
  {
    "MateriaGroupId": 3,
    "MateriaId": 2152007
  },
  {
    "MateriaGroupId": 3,
    "MateriaId": 2152008
  },
  {
    "MateriaGroupId": 3,
    "MateriaId": 2152009
  },
  {
    "MateriaGroupId": 3,
    "MateriaId": 2152010
  },
  {
    "MateriaGroupId": 3,
    "MateriaId": 2161002
  },
  {
    "MateriaGroupId": 3,
    "MateriaId": 2162002
  },
  {
    "MateriaGroupId": 3,
    "MateriaId": 2162007
  },
  {
    "MateriaGroupId": 3,
    "MateriaId": 2162008
  },
  {
    "MateriaGroupId": 3,
    "MateriaId": 2162009
  },
  {
    "MateriaGroupId": 3,
    "MateriaId": 2162010
  },
  {
    "MateriaGroupId": 4,
    "MateriaId": 2101001
  },
  {
    "MateriaGroupId": 4,
    "MateriaId": 2101003
  },
  {
    "MateriaGroupId": 4,
    "MateriaId": 2102001
  },
  {
    "MateriaGroupId": 4,
    "MateriaId": 2102003
  },
  {
    "MateriaGroupId": 4,
    "MateriaId": 2111001
  },
  {
    "MateriaGroupId": 4,
    "MateriaId": 2111003
  },
  {
    "MateriaGroupId": 4,
    "MateriaId": 2111007
  },
  {
    "MateriaGroupId": 4,
    "MateriaId": 2112001
  },
  {
    "MateriaGroupId": 4,
    "MateriaId": 2112003
  },
  {
    "MateriaGroupId": 4,
    "MateriaId": 2112004
  },
  {
    "MateriaGroupId": 4,
    "MateriaId": 2112005
  },
  {
    "MateriaGroupId": 4,
    "MateriaId": 2112006
  },
  {
    "MateriaGroupId": 4,
    "MateriaId": 2112007
  },
  {
    "MateriaGroupId": 4,
    "MateriaId": 2112008
  },
  {
    "MateriaGroupId": 4,
    "MateriaId": 2112009
  },
  {
    "MateriaGroupId": 4,
    "MateriaId": 2112010
  },
  {
    "MateriaGroupId": 4,
    "MateriaId": 2112011
  },
  {
    "MateriaGroupId": 4,
    "MateriaId": 2121001
  },
  {
    "MateriaGroupId": 4,
    "MateriaId": 2121003
  },
  {
    "MateriaGroupId": 4,
    "MateriaId": 2121007
  },
  {
    "MateriaGroupId": 4,
    "MateriaId": 2122001
  },
  {
    "MateriaGroupId": 4,
    "MateriaId": 2122003
  },
  {
    "MateriaGroupId": 4,
    "MateriaId": 2122004
  },
  {
    "MateriaGroupId": 4,
    "MateriaId": 2122005
  },
  {
    "MateriaGroupId": 4,
    "MateriaId": 2122006
  },
  {
    "MateriaGroupId": 4,
    "MateriaId": 2122007
  },
  {
    "MateriaGroupId": 4,
    "MateriaId": 2122008
  },
  {
    "MateriaGroupId": 4,
    "MateriaId": 2122009
  },
  {
    "MateriaGroupId": 4,
    "MateriaId": 2122010
  },
  {
    "MateriaGroupId": 4,
    "MateriaId": 2122011
  },
  {
    "MateriaGroupId": 4,
    "MateriaId": 2131001
  },
  {
    "MateriaGroupId": 4,
    "MateriaId": 2131003
  },
  {
    "MateriaGroupId": 4,
    "MateriaId": 2131007
  },
  {
    "MateriaGroupId": 4,
    "MateriaId": 2132001
  },
  {
    "MateriaGroupId": 4,
    "MateriaId": 2132003
  },
  {
    "MateriaGroupId": 4,
    "MateriaId": 2132004
  },
  {
    "MateriaGroupId": 4,
    "MateriaId": 2132005
  },
  {
    "MateriaGroupId": 4,
    "MateriaId": 2132006
  },
  {
    "MateriaGroupId": 4,
    "MateriaId": 2132007
  },
  {
    "MateriaGroupId": 4,
    "MateriaId": 2132008
  },
  {
    "MateriaGroupId": 4,
    "MateriaId": 2132009
  },
  {
    "MateriaGroupId": 4,
    "MateriaId": 2132010
  },
  {
    "MateriaGroupId": 4,
    "MateriaId": 2132011
  },
  {
    "MateriaGroupId": 4,
    "MateriaId": 2141001
  },
  {
    "MateriaGroupId": 4,
    "MateriaId": 2141002
  },
  {
    "MateriaGroupId": 4,
    "MateriaId": 2141007
  },
  {
    "MateriaGroupId": 4,
    "MateriaId": 2142001
  },
  {
    "MateriaGroupId": 4,
    "MateriaId": 2142002
  },
  {
    "MateriaGroupId": 4,
    "MateriaId": 2142003
  },
  {
    "MateriaGroupId": 4,
    "MateriaId": 2142004
  },
  {
    "MateriaGroupId": 4,
    "MateriaId": 2142005
  },
  {
    "MateriaGroupId": 4,
    "MateriaId": 2142006
  },
  {
    "MateriaGroupId": 4,
    "MateriaId": 2142007
  },
  {
    "MateriaGroupId": 4,
    "MateriaId": 2142008
  },
  {
    "MateriaGroupId": 4,
    "MateriaId": 2142009
  },
  {
    "MateriaGroupId": 4,
    "MateriaId": 2142010
  },
  {
    "MateriaGroupId": 4,
    "MateriaId": 2151001
  },
  {
    "MateriaGroupId": 4,
    "MateriaId": 2151002
  },
  {
    "MateriaGroupId": 4,
    "MateriaId": 2151007
  },
  {
    "MateriaGroupId": 4,
    "MateriaId": 2152001
  },
  {
    "MateriaGroupId": 4,
    "MateriaId": 2152002
  },
  {
    "MateriaGroupId": 4,
    "MateriaId": 2152003
  },
  {
    "MateriaGroupId": 4,
    "MateriaId": 2152004
  },
  {
    "MateriaGroupId": 4,
    "MateriaId": 2152005
  },
  {
    "MateriaGroupId": 4,
    "MateriaId": 2152006
  },
  {
    "MateriaGroupId": 4,
    "MateriaId": 2152007
  },
  {
    "MateriaGroupId": 4,
    "MateriaId": 2152008
  },
  {
    "MateriaGroupId": 4,
    "MateriaId": 2152009
  },
  {
    "MateriaGroupId": 4,
    "MateriaId": 2152010
  },
  {
    "MateriaGroupId": 4,
    "MateriaId": 2161001
  },
  {
    "MateriaGroupId": 4,
    "MateriaId": 2161002
  },
  {
    "MateriaGroupId": 4,
    "MateriaId": 2161007
  },
  {
    "MateriaGroupId": 4,
    "MateriaId": 2162001
  },
  {
    "MateriaGroupId": 4,
    "MateriaId": 2162002
  },
  {
    "MateriaGroupId": 4,
    "MateriaId": 2162003
  },
  {
    "MateriaGroupId": 4,
    "MateriaId": 2162004
  },
  {
    "MateriaGroupId": 4,
    "MateriaId": 2162005
  },
  {
    "MateriaGroupId": 4,
    "MateriaId": 2162006
  },
  {
    "MateriaGroupId": 4,
    "MateriaId": 2162007
  },
  {
    "MateriaGroupId": 4,
    "MateriaId": 2162008
  },
  {
    "MateriaGroupId": 4,
    "MateriaId": 2162009
  },
  {
    "MateriaGroupId": 4,
    "MateriaId": 2162010
  },
  {
    "MateriaGroupId": 4,
    "MateriaId": 2501001
  },
  {
    "MateriaGroupId": 4,
    "MateriaId": 2601001
  },
  {
    "MateriaGroupId": 4,
    "MateriaId": 2601002
  },
  {
    "MateriaGroupId": 4,
    "MateriaId": 2601003
  },
  {
    "MateriaGroupId": 4,
    "MateriaId": 2601004
  },
  {
    "MateriaGroupId": 4,
    "MateriaId": 2601005
  },
  {
    "MateriaGroupId": 4,
    "MateriaId": 2601006
  },
  {
    "MateriaGroupId": 4,
    "MateriaId": 2601007
  },
  {
    "MateriaGroupId": 4,
    "MateriaId": 2601008
  },
  {
    "MateriaGroupId": 4,
    "MateriaId": 2601009
  },
  {
    "MateriaGroupId": 4,
    "MateriaId": 2601010
  },
  {
    "MateriaGroupId": 5,
    "MateriaId": 2200001
  },
  {
    "MateriaGroupId": 5,
    "MateriaId": 2300001
  },
  {
    "MateriaGroupId": 5,
    "MateriaId": 2300002
  },
  {
    "MateriaGroupId": 5,
    "MateriaId": 2400001
  },
  {
    "MateriaGroupId": 5,
    "MateriaId": 2400002
  },
  {
    "MateriaGroupId": 5,
    "MateriaId": 2400003
  },
  {
    "MateriaGroupId": 5,
    "MateriaId": 2400004
  },
  {
    "MateriaGroupId": 5,
    "MateriaId": 2400005
  },
  {
    "MateriaGroupId": 5,
    "MateriaId": 2601011
  },
  {
    "MateriaGroupId": 6,
    "MateriaId": 2300001
  },
  {
    "MateriaGroupId": 6,
    "MateriaId": 2300002
  },
  {
    "MateriaGroupId": 6,
    "MateriaId": 2501001
  },
  {
    "MateriaGroupId": 6,
    "MateriaId": 2601001
  },
  {
    "MateriaGroupId": 6,
    "MateriaId": 2601002
  },
  {
    "MateriaGroupId": 6,
    "MateriaId": 2601003
  },
  {
    "MateriaGroupId": 6,
    "MateriaId": 2601004
  },
  {
    "MateriaGroupId": 6,
    "MateriaId": 2601005
  },
  {
    "MateriaGroupId": 6,
    "MateriaId": 2601006
  },
  {
    "MateriaGroupId": 6,
    "MateriaId": 2601007
  },
  {
    "MateriaGroupId": 6,
    "MateriaId": 2601008
  },
  {
    "MateriaGroupId": 6,
    "MateriaId": 2601009
  },
  {
    "MateriaGroupId": 6,
    "MateriaId": 2601010
  },
  {
    "MateriaGroupId": 6,
    "MateriaId": 2601011
  },
  {
    "MateriaGroupId": 7,
    "MateriaId": 2102001
  },
  {
    "MateriaGroupId": 7,
    "MateriaId": 2102003
  },
  {
    "MateriaGroupId": 7,
    "MateriaId": 2112001
  },
  {
    "MateriaGroupId": 7,
    "MateriaId": 2112003
  },
  {
    "MateriaGroupId": 7,
    "MateriaId": 2112004
  },
  {
    "MateriaGroupId": 7,
    "MateriaId": 2112005
  },
  {
    "MateriaGroupId": 7,
    "MateriaId": 2112006
  },
  {
    "MateriaGroupId": 7,
    "MateriaId": 2112007
  },
  {
    "MateriaGroupId": 7,
    "MateriaId": 2112008
  },
  {
    "MateriaGroupId": 7,
    "MateriaId": 2112009
  },
  {
    "MateriaGroupId": 7,
    "MateriaId": 2112010
  },
  {
    "MateriaGroupId": 7,
    "MateriaId": 2112011
  },
  {
    "MateriaGroupId": 7,
    "MateriaId": 2122001
  },
  {
    "MateriaGroupId": 7,
    "MateriaId": 2122003
  },
  {
    "MateriaGroupId": 7,
    "MateriaId": 2122004
  },
  {
    "MateriaGroupId": 7,
    "MateriaId": 2122005
  },
  {
    "MateriaGroupId": 7,
    "MateriaId": 2122006
  },
  {
    "MateriaGroupId": 7,
    "MateriaId": 2122007
  },
  {
    "MateriaGroupId": 7,
    "MateriaId": 2122008
  },
  {
    "MateriaGroupId": 7,
    "MateriaId": 2122009
  },
  {
    "MateriaGroupId": 7,
    "MateriaId": 2122010
  },
  {
    "MateriaGroupId": 7,
    "MateriaId": 2122011
  },
  {
    "MateriaGroupId": 7,
    "MateriaId": 2132001
  },
  {
    "MateriaGroupId": 7,
    "MateriaId": 2132003
  },
  {
    "MateriaGroupId": 7,
    "MateriaId": 2132004
  },
  {
    "MateriaGroupId": 7,
    "MateriaId": 2132005
  },
  {
    "MateriaGroupId": 7,
    "MateriaId": 2132006
  },
  {
    "MateriaGroupId": 7,
    "MateriaId": 2132007
  },
  {
    "MateriaGroupId": 7,
    "MateriaId": 2132008
  },
  {
    "MateriaGroupId": 7,
    "MateriaId": 2132009
  },
  {
    "MateriaGroupId": 7,
    "MateriaId": 2132010
  },
  {
    "MateriaGroupId": 7,
    "MateriaId": 2132011
  },
  {
    "MateriaGroupId": 7,
    "MateriaId": 2142001
  },
  {
    "MateriaGroupId": 7,
    "MateriaId": 2142002
  },
  {
    "MateriaGroupId": 7,
    "MateriaId": 2142003
  },
  {
    "MateriaGroupId": 7,
    "MateriaId": 2142004
  },
  {
    "MateriaGroupId": 7,
    "MateriaId": 2142005
  },
  {
    "MateriaGroupId": 7,
    "MateriaId": 2142006
  },
  {
    "MateriaGroupId": 7,
    "MateriaId": 2142007
  },
  {
    "MateriaGroupId": 7,
    "MateriaId": 2142008
  },
  {
    "MateriaGroupId": 7,
    "MateriaId": 2142009
  },
  {
    "MateriaGroupId": 7,
    "MateriaId": 2142010
  },
  {
    "MateriaGroupId": 7,
    "MateriaId": 2152001
  },
  {
    "MateriaGroupId": 7,
    "MateriaId": 2152002
  },
  {
    "MateriaGroupId": 7,
    "MateriaId": 2152003
  },
  {
    "MateriaGroupId": 7,
    "MateriaId": 2152004
  },
  {
    "MateriaGroupId": 7,
    "MateriaId": 2152005
  },
  {
    "MateriaGroupId": 7,
    "MateriaId": 2152006
  },
  {
    "MateriaGroupId": 7,
    "MateriaId": 2152007
  },
  {
    "MateriaGroupId": 7,
    "MateriaId": 2152008
  },
  {
    "MateriaGroupId": 7,
    "MateriaId": 2152009
  },
  {
    "MateriaGroupId": 7,
    "MateriaId": 2152010
  },
  {
    "MateriaGroupId": 7,
    "MateriaId": 2162001
  },
  {
    "MateriaGroupId": 7,
    "MateriaId": 2162002
  },
  {
    "MateriaGroupId": 7,
    "MateriaId": 2162003
  },
  {
    "MateriaGroupId": 7,
    "MateriaId": 2162004
  },
  {
    "MateriaGroupId": 7,
    "MateriaId": 2162005
  },
  {
    "MateriaGroupId": 7,
    "MateriaId": 2162006
  },
  {
    "MateriaGroupId": 7,
    "MateriaId": 2162007
  },
  {
    "MateriaGroupId": 7,
    "MateriaId": 2162008
  },
  {
    "MateriaGroupId": 7,
    "MateriaId": 2162009
  },
  {
    "MateriaGroupId": 7,
    "MateriaId": 2162010
  },
  {
    "MateriaGroupId": 11,
    "MateriaId": 2111001
  },
  {
    "MateriaGroupId": 11,
    "MateriaId": 2111003
  },
  {
    "MateriaGroupId": 11,
    "MateriaId": 2111007
  },
  {
    "MateriaGroupId": 11,
    "MateriaId": 2112001
  },
  {
    "MateriaGroupId": 11,
    "MateriaId": 2112003
  },
  {
    "MateriaGroupId": 11,
    "MateriaId": 2112004
  },
  {
    "MateriaGroupId": 11,
    "MateriaId": 2112005
  },
  {
    "MateriaGroupId": 11,
    "MateriaId": 2112006
  },
  {
    "MateriaGroupId": 11,
    "MateriaId": 2112007
  },
  {
    "MateriaGroupId": 11,
    "MateriaId": 2112008
  },
  {
    "MateriaGroupId": 11,
    "MateriaId": 2112009
  },
  {
    "MateriaGroupId": 11,
    "MateriaId": 2112010
  },
  {
    "MateriaGroupId": 11,
    "MateriaId": 2112011
  },
  {
    "MateriaGroupId": 12,
    "MateriaId": 2121001
  },
  {
    "MateriaGroupId": 12,
    "MateriaId": 2121003
  },
  {
    "MateriaGroupId": 12,
    "MateriaId": 2121007
  },
  {
    "MateriaGroupId": 12,
    "MateriaId": 2122001
  },
  {
    "MateriaGroupId": 12,
    "MateriaId": 2122003
  },
  {
    "MateriaGroupId": 12,
    "MateriaId": 2122004
  },
  {
    "MateriaGroupId": 12,
    "MateriaId": 2122005
  },
  {
    "MateriaGroupId": 12,
    "MateriaId": 2122006
  },
  {
    "MateriaGroupId": 12,
    "MateriaId": 2122007
  },
  {
    "MateriaGroupId": 12,
    "MateriaId": 2122008
  },
  {
    "MateriaGroupId": 12,
    "MateriaId": 2122009
  },
  {
    "MateriaGroupId": 12,
    "MateriaId": 2122010
  },
  {
    "MateriaGroupId": 12,
    "MateriaId": 2122011
  },
  {
    "MateriaGroupId": 13,
    "MateriaId": 2131001
  },
  {
    "MateriaGroupId": 13,
    "MateriaId": 2131003
  },
  {
    "MateriaGroupId": 13,
    "MateriaId": 2131007
  },
  {
    "MateriaGroupId": 13,
    "MateriaId": 2132001
  },
  {
    "MateriaGroupId": 13,
    "MateriaId": 2132003
  },
  {
    "MateriaGroupId": 13,
    "MateriaId": 2132004
  },
  {
    "MateriaGroupId": 13,
    "MateriaId": 2132005
  },
  {
    "MateriaGroupId": 13,
    "MateriaId": 2132006
  },
  {
    "MateriaGroupId": 13,
    "MateriaId": 2132007
  },
  {
    "MateriaGroupId": 13,
    "MateriaId": 2132008
  },
  {
    "MateriaGroupId": 13,
    "MateriaId": 2132009
  },
  {
    "MateriaGroupId": 13,
    "MateriaId": 2132010
  },
  {
    "MateriaGroupId": 13,
    "MateriaId": 2132011
  },
  {
    "MateriaGroupId": 14,
    "MateriaId": 2151001
  },
  {
    "MateriaGroupId": 14,
    "MateriaId": 2151002
  },
  {
    "MateriaGroupId": 14,
    "MateriaId": 2151007
  },
  {
    "MateriaGroupId": 14,
    "MateriaId": 2152001
  },
  {
    "MateriaGroupId": 14,
    "MateriaId": 2152002
  },
  {
    "MateriaGroupId": 14,
    "MateriaId": 2152003
  },
  {
    "MateriaGroupId": 14,
    "MateriaId": 2152004
  },
  {
    "MateriaGroupId": 14,
    "MateriaId": 2152005
  },
  {
    "MateriaGroupId": 14,
    "MateriaId": 2152006
  },
  {
    "MateriaGroupId": 14,
    "MateriaId": 2152007
  },
  {
    "MateriaGroupId": 14,
    "MateriaId": 2152008
  },
  {
    "MateriaGroupId": 14,
    "MateriaId": 2152009
  },
  {
    "MateriaGroupId": 14,
    "MateriaId": 2152010
  },
  {
    "MateriaGroupId": 15,
    "MateriaId": 2161001
  },
  {
    "MateriaGroupId": 15,
    "MateriaId": 2161002
  },
  {
    "MateriaGroupId": 15,
    "MateriaId": 2161007
  },
  {
    "MateriaGroupId": 15,
    "MateriaId": 2162001
  },
  {
    "MateriaGroupId": 15,
    "MateriaId": 2162002
  },
  {
    "MateriaGroupId": 15,
    "MateriaId": 2162003
  },
  {
    "MateriaGroupId": 15,
    "MateriaId": 2162004
  },
  {
    "MateriaGroupId": 15,
    "MateriaId": 2162005
  },
  {
    "MateriaGroupId": 15,
    "MateriaId": 2162006
  },
  {
    "MateriaGroupId": 15,
    "MateriaId": 2162007
  },
  {
    "MateriaGroupId": 15,
    "MateriaId": 2162008
  },
  {
    "MateriaGroupId": 15,
    "MateriaId": 2162009
  },
  {
    "MateriaGroupId": 15,
    "MateriaId": 2162010
  },
  {
    "MateriaGroupId": 16,
    "MateriaId": 2141001
  },
  {
    "MateriaGroupId": 16,
    "MateriaId": 2141002
  },
  {
    "MateriaGroupId": 16,
    "MateriaId": 2141007
  },
  {
    "MateriaGroupId": 16,
    "MateriaId": 2142001
  },
  {
    "MateriaGroupId": 16,
    "MateriaId": 2142002
  },
  {
    "MateriaGroupId": 16,
    "MateriaId": 2142003
  },
  {
    "MateriaGroupId": 16,
    "MateriaId": 2142004
  },
  {
    "MateriaGroupId": 16,
    "MateriaId": 2142005
  },
  {
    "MateriaGroupId": 16,
    "MateriaId": 2142006
  },
  {
    "MateriaGroupId": 16,
    "MateriaId": 2142007
  },
  {
    "MateriaGroupId": 16,
    "MateriaId": 2142008
  },
  {
    "MateriaGroupId": 16,
    "MateriaId": 2142009
  },
  {
    "MateriaGroupId": 16,
    "MateriaId": 2142010
  },
  {
    "MateriaGroupId": 51001,
    "MateriaId": 2200001
  },
  {
    "MateriaGroupId": 51701,
    "MateriaId": 2400001
  },
  {
    "MateriaGroupId": 51701,
    "MateriaId": 2400002
  },
  {
    "MateriaGroupId": 51701,
    "MateriaId": 2400003
  },
  {
    "MateriaGroupId": 51701,
    "MateriaId": 2400004
  },
  {
    "MateriaGroupId": 51701,
    "MateriaId": 2400005
  }
]